charmlibs/__init__.py
charmlibs-1.0.0a1.dist-info/METADATA
charmlibs-1.0.0a1.dist-info/WHEEL
charmlibs-1.0.0a1.dist-info/top_level.txt
charmlibs-1.0.0a1.dist-info/RECORD
