Metadata-Version: 2.4
Name: charmlibs
Version: 1.0.0a1
Summary: The charmlibs namespace. This package should not be installed.
Author: The Charm Tech team at Canonical Ltd.
Project-URL: Documentation, https://documentation.ubuntu.com/charmlibs
Project-URL: Repository, https://github.com/canonical/charmlibs
Project-URL: Issues, https://github.com/canonical/charmlibs/issues
Classifier: Programming Language :: Python :: 3
Classifier: License :: OSI Approved :: Apache Software License
Classifier: Intended Audience :: Developers
Classifier: Operating System :: POSIX :: Linux
Classifier: Development Status :: 5 - Production/Stable
Requires-Python: >=3.10
